{"_type":"export","__export_format":4,"__export_date":"2022-05-07T15:53:53.346Z","__export_source":"insomnia.desktop.app:v2022.3.0","resources":[{"_id":"req_b0b22494d24b491aa976f71355c61e08","parentId":"fld_9dd5f57987c14e0ba2d4a3af834e504c","modified":1651938177621,"created":1651938172396,"url":"{{ _.beseUrl }}/physiotherapist/","name":"findAll","description":"","method":"GET","body":{},"parameters":[],"headers":[],"authentication":{},"metaSortKey":-1651938172396,"isPrivate":false,"settingStoreCookies":true,"settingSendCookies":true,"settingDisableRenderRequestBody":false,"settingEncodeUrl":true,"settingRebuildPath":true,"settingFollowRedirects":"global","_type":"request"},{"_id":"fld_9dd5f57987c14e0ba2d4a3af834e504c","parentId":"wrk_75446acf89ae4010a65f63f5d22b1731","modified":1651934749761,"created":1651934749761,"name":"Patient","description":"","environment":{},"environmentPropertyOrder":null,"metaSortKey":-1651934749761,"_type":"request_group"},{"_id":"wrk_75446acf89ae4010a65f63f5d22b1731","parentId":null,"modified":1647435365529,"created":1647435365529,"name":"New Document","description":"","scope":"design","_type":"workspace"},{"_id":"req_c0a3c45b4fd745feba86a55428dd95a3","parentId":"fld_9dd5f57987c14e0ba2d4a3af834e504c","modified":1651937894433,"created":1651937874373,"url":"{{ _.beseUrl }}/physiotherapist/","name":"findOne","description":"","method":"GET","body":{},"parameters":[],"headers":[],"authentication":{},"metaSortKey":-1651937874373,"isPrivate":false,"settingStoreCookies":true,"settingSendCookies":true,"settingDisableRenderRequestBody":false,"settingEncodeUrl":true,"settingRebuildPath":true,"settingFollowRedirects":"global","_type":"request"},{"_id":"req_754fbfb358174a3ab5c7bcc28ebbe25a","parentId":"fld_9dd5f57987c14e0ba2d4a3af834e504c","modified":1651938696352,"created":1651934823155,"url":"{{ _.beseUrl }}/physiotherapist/info","name":"Create","description":"","method":"POST","body":{"mimeType":"application/json","text":"{\n\t\"name\": \"wellington2\",\n\t\"password\": \"1234\",\n\t\"coffito\": \"1234564\"\n}"},"parameters":[],"headers":[{"name":"Content-Type","value":"application/json","id":"pair_90f383a881974cc1b8f44d74dc51780e"}],"authentication":{},"metaSortKey":-1651934823155,"isPrivate":false,"settingStoreCookies":true,"settingSendCookies":true,"settingDisableRenderRequestBody":false,"settingEncodeUrl":true,"settingRebuildPath":true,"settingFollowRedirects":"global","_type":"request"},{"_id":"req_f6ba87ad33c84ca69a7cab32b2fea9bc","parentId":"fld_82efe6ee7d4446b39fe76db3f286eb26","modified":1651934930081,"created":1647435365618,"url":"{{ _.beseUrl }}/signin","name":"Signin","description":"","method":"POST","body":{"mimeType":"application/json","text":"{\n\t\"coffito\": \"123456\",\n\t\"password\": \"1234\"\n}"},"parameters":[],"headers":[{"name":"Content-Type","value":"application/json","id":"pair_02bbcd68e68d44a9845553f406b55e3c"}],"authentication":{},"metaSortKey":-1647435365618,"isPrivate":false,"settingStoreCookies":true,"settingSendCookies":true,"settingDisableRenderRequestBody":false,"settingEncodeUrl":true,"settingRebuildPath":true,"settingFollowRedirects":"global","_type":"request"},{"_id":"fld_82efe6ee7d4446b39fe76db3f286eb26","parentId":"wrk_75446acf89ae4010a65f63f5d22b1731","modified":1651934741147,"created":1651934741147,"name":"Sign in","description":"","environment":{},"environmentPropertyOrder":null,"metaSortKey":-1651934741147,"_type":"request_group"},{"_id":"env_c9083e4a8a37baf21a895498d70d38b93b9048d1","parentId":"wrk_75446acf89ae4010a65f63f5d22b1731","modified":1651934409493,"created":1647435365587,"name":"Base Environment","data":{"beseUrl":"http://localhost:3001"},"dataPropertyOrder":{"&":["beseUrl"]},"color":null,"isPrivate":false,"metaSortKey":1647435365587,"_type":"environment"},{"_id":"jar_c9083e4a8a37baf21a895498d70d38b93b9048d1","parentId":"wrk_75446acf89ae4010a65f63f5d22b1731","modified":1647435365603,"created":1647435365603,"name":"Default Jar","cookies":[],"_type":"cookie_jar"},{"_id":"spc_ce37d0ce6d3f40af8aa027b7a662a8c4","parentId":"wrk_75446acf89ae4010a65f63f5d22b1731","modified":1651934293524,"created":1647435365571,"fileName":"New Document","contents":"","contentType":"yaml","_type":"api_spec"},{"_id":"uts_1b0080c3eb5d49c4a151545b5df23c90","parentId":"wrk_75446acf89ae4010a65f63f5d22b1731","modified":1647435365623,"created":1647435365623,"name":"Example Test Suite","_type":"unit_test_suite"},{"_id":"env_df12f88131a64523808c6c243139b659","parentId":"env_c9083e4a8a37baf21a895498d70d38b93b9048d1","modified":1651934426081,"created":1651934413315,"name":"Dev","data":{"beseUrl":"http://localhost:3001"},"dataPropertyOrder":{"&":["beseUrl"]},"color":"#c328d7","isPrivate":false,"metaSortKey":1651934413315,"_type":"environment"}]}